genomehubs/__init__.py
genomehubs/__main__.py
genomehubs/genomehubs.py
genomehubs/py.typed
genomehubs/config/dist.config.yaml
genomehubs/lib/__init__.py
genomehubs/lib/analysis.py
genomehubs/lib/attributes.py
genomehubs/lib/btk.py
genomehubs/lib/busco.py
genomehubs/lib/config.py
genomehubs/lib/directory.py
genomehubs/lib/es_functions.py
genomehubs/lib/feature.py
genomehubs/lib/files.py
genomehubs/lib/fill.py
genomehubs/lib/gbif.py
genomehubs/lib/geo.py
genomehubs/lib/hub.py
genomehubs/lib/index.py
genomehubs/lib/init.py
genomehubs/lib/ncbi.py
genomehubs/lib/parse.py
genomehubs/lib/run.py
genomehubs/lib/sample.py
genomehubs/lib/search.py
genomehubs/lib/taxon.py
genomehubs/lib/taxonomy.py
genomehubs/lib/test.py
genomehubs/lib/utils.py
genomehubs/lib/validate.py
genomehubs/lib/version.py
genomehubs/lib/wikidata.py
genomehubs/lib/window.py
genomehubs/templates/ATTR_ancestral_unit.types.yaml
genomehubs/templates/ATTR_assembly.types.yaml
genomehubs/templates/ATTR_btk.types.yaml
genomehubs/templates/ATTR_busco.types.yaml
genomehubs/templates/ATTR_feature.types.yaml
genomehubs/templates/ATTR_sample.types.yaml
genomehubs/templates/ATTR_sra.types.yaml
genomehubs/templates/ATTR_window_stats.types.yaml
genomehubs/templates/TAXON_assembly.types.yaml
genomehubs/templates/analysis.json
genomehubs/templates/assembly.json
genomehubs/templates/assembly.types.yaml
genomehubs/templates/attributes.json
genomehubs/templates/btk.types.yaml
genomehubs/templates/busco.types.yaml
genomehubs/templates/busco_feature.types.yaml
genomehubs/templates/feature.json
genomehubs/templates/file.json
genomehubs/templates/identifiers.json
genomehubs/templates/organelle.types.yaml
genomehubs/templates/sample.json
genomehubs/templates/sample.types.yaml
genomehubs/templates/sra.types.yaml
genomehubs/templates/taxon.json
genomehubs/templates/taxon.types.yaml
genomehubs/templates/taxonomy.json
genomehubs/templates/wikidata.names.yaml
genomehubs/templates/window_full.types.yaml
genomehubs-2.11.17.dist-info/licenses/AUTHORS
genomehubs-2.11.17.dist-info/licenses/AUTHORS.rst
genomehubs-2.11.17.dist-info/licenses/LICENSE
genomehubs-2.11.17.dist-info/METADATA
genomehubs-2.11.17.dist-info/WHEEL
genomehubs-2.11.17.dist-info/entry_points.txt
genomehubs-2.11.17.dist-info/top_level.txt
genomehubs-2.11.17.dist-info/RECORD
