Metadata-Version: 2.4
Name: genomehubs
Version: 2.11.17
Summary: GenomeHubs
Home-page: https://github.com/genomehubs/genomehubs
Author: genomehubs
Author-email: genomehubs@genomehubs.org
Project-URL: Bug Reports, https://github.com/genomehubs/genomehubs/issues
Project-URL: Source, https://github.com/genomehubs/genomehubs
Keywords: bioinformatics
Classifier: Development Status :: 5 - Production/Stable
Classifier: Intended Audience :: Science/Research
Classifier: Topic :: Scientific/Engineering :: Bio-Informatics
Classifier: License :: OSI Approved :: MIT License
Classifier: Programming Language :: Python :: 3
Classifier: Programming Language :: Python :: 3.8
Classifier: Programming Language :: Python :: 3.9
Classifier: Programming Language :: Python :: 3.10
Classifier: Programming Language :: Python :: 3 :: Only
Requires-Python: >=3.6, <4
License-File: LICENSE
License-File: AUTHORS
License-File: AUTHORS.rst
Requires-Dist: biopython>=1.78
Requires-Dist: boto3>=1.34.84
Requires-Dist: docopt>=0.6.2
Requires-Dist: elasticsearch==8.7
Requires-Dist: fastjsonschema>=2.15.3
Requires-Dist: filetype>=1.0.7
Requires-Dist: h3>=4.2.2
Requires-Dist: Pillow>=8.0
Requires-Dist: pyyaml
Requires-Dist: sparqlwrapper>=1.4.1
Requires-Dist: tolkein>=0.5.0
Requires-Dist: ujson>=3.0.0
Requires-Dist: urllib3<2,>=1.26.2
Provides-Extra: dev
Requires-Dist: pycodestyle>=2.6.0; extra == "dev"
Requires-Dist: pydocstyle>=5.0.2; extra == "dev"
Requires-Dist: pylint>=2.5.3; extra == "dev"
Provides-Extra: test
Requires-Dist: coverage>=5.1; extra == "test"
Requires-Dist: coveralls>=2.0.0; extra == "test"
Requires-Dist: mock>=4.0.2; extra == "test"
Requires-Dist: pytest-cov>=2.10.0; extra == "test"
Requires-Dist: pytest-isort>=1.1.0; extra == "test"
Requires-Dist: pytest-mock>=3.1.1; extra == "test"
Requires-Dist: pytest>=6.0.0; extra == "test"
Dynamic: author
Dynamic: author-email
Dynamic: classifier
Dynamic: description
Dynamic: description-content-type
Dynamic: home-page
Dynamic: keywords
Dynamic: license-file
Dynamic: project-url
Dynamic: provides-extra
Dynamic: requires-dist
Dynamic: requires-python
Dynamic: summary
